{
    "temperature": 9.5,
    "temp_max": 18.9,
    "temp_min": 8.2,
    "humidity": 76,
    "pressure": 1024.2,
    "dew_point": 4.7,
    "wind_speed": 3.2,
    "wind_gust": 11.2,
    "wind_dir": 286,
    "wind_text": "286° Δ",
    "rain": 0.0,
    "clouds": 3,
    "status": "ΞΑΣΤΕΡΙΑ.ΑΙΘΡΙΟΣ",
    "moon_icon": "moon7.png",
    "time": "07:30:30",
    "last_update": "07:30:30",
    "peak_temp": 9.5,
    "peak_status": "ΞΑΣΤΕΡΙΑ.ΑΙΘΡΙΟΣ",
    "feels_like": 9.5,
    "wind_info": "Δ 3.2 km/h",
    "model_forecast": "ΠΙΘΑΝΗ ΕΠΙΔΕΙΝΩΣΗ ΑΠΟ ΤΕΤΑΡΤΗ"
}