{
    "temperature": 8.6,
    "temp_max": 12.8,
    "temp_min": 7.3,
    "humidity": 99,
    "pressure": 1024.5,
    "dew_point": 8.4,
    "wind_speed": 4.5,
    "wind_gust": 10.4,
    "wind_dir": 40,
    "wind_text": "40° ΒΑ",
    "rain": 0.9,
    "clouds": 100,
    "status": "ΒΡΟΧΗ",
    "moon_icon": "moon2.png",
    "time": "21:15:28",
    "last_update": "21:15:28",
    "peak_temp": 8.6,
    "peak_status": "ΒΡΟΧΗ",
    "feels_like": 8.6,
    "wind_info": "ΒΑ 4.5 km/h",
    "model_forecast": "ΠΡΟΣΟΧΗ: ΦΑΙΝΟΜΕΝΑ ΣΕ ΕΞΕΛΙΞΗ"
}