{
    "temperature": 25.9,
    "temp_max": 27.2,
    "temp_min": 18.4,
    "humidity": 43,
    "pressure": 1029.6,
    "dew_point": 14.5,
    "wind_speed": 7.7,
    "wind_gust": 22.3,
    "wind_dir": 311,
    "wind_text": "311° ΒΔ",
    "rain": 0.0,
    "clouds": 17,
    "status": "ΞΑΣΤΕΡΙΑ.ΑΙΘΡΙΟΣ",
    "moon_icon": "moon6.png",
    "time": "13:01:11",
    "last_update": "13:01:11",
    "peak_temp": 25.9,
    "peak_status": "ΞΑΣΤΕΡΙΑ.ΑΙΘΡΙΟΣ",
    "feels_like": 25.9,
    "wind_info": "ΒΔ 7.7 km/h",
    "model_forecast": "ΞΑΣΤΕΡΙΑ.ΑΙΘΡΙΟΣ"
}