{
    "temperature": 18.3,
    "temp_max": 20.3,
    "temp_min": 11.8,
    "humidity": 75,
    "pressure": 1032.1,
    "dew_point": 13.3,
    "wind_speed": 7.3,
    "wind_gust": 32.4,
    "wind_dir": 80,
    "wind_text": "80° Α",
    "rain": 0.1,
    "clouds": 55,
    "status": "ΒΡΟΧΗ",
    "moon_icon": "moon2.png",
    "time": "14:15:27",
    "last_update": "14:15:27",
    "peak_temp": 18.3,
    "peak_status": "ΒΡΟΧΗ",
    "feels_like": 18.3,
    "wind_info": "Α 7.3 km/h",
    "model_forecast": "ΠΙΘΑΝΗ ΕΠΙΔΕΙΝΩΣΗ ΑΠΟ ΚΥΡΙΑΚΗ"
}