{
    "temperature": 15.5,
    "temp_max": 16.4,
    "temp_min": 8.7,
    "humidity": 65,
    "pressure": 1025.4,
    "dew_point": 8.5,
    "wind_speed": 6.5,
    "wind_gust": 28.8,
    "wind_dir": 44,
    "wind_text": "44° ΒΑ",
    "rain": 0.6,
    "clouds": 38,
    "status": "ΒΡΟΧΗ",
    "moon_icon": "moon7.png",
    "time": "15:45:27",
    "last_update": "15:45:27",
    "peak_temp": 15.5,
    "peak_status": "ΒΡΟΧΗ",
    "feels_like": 15.5,
    "wind_info": "ΒΑ 6.5 km/h",
    "model_forecast": "ΠΡΟΣΟΧΗ: ΦΑΙΝΟΜΕΝΑ ΣΕ ΕΞΕΛΙΞΗ"
}