{
    "temperature": 11.0,
    "temp_max": 18.9,
    "temp_min": 10.4,
    "humidity": 44,
    "pressure": 1028.1,
    "dew_point": -0.2,
    "wind_speed": 9.8,
    "wind_gust": 31.3,
    "wind_dir": 294,
    "wind_text": "294° ΒΔ",
    "rain": 0.0,
    "clouds": 2,
    "status": "ΞΑΣΤΕΡΙΑ.ΑΙΘΡΙΟΣ",
    "moon_icon": "moon6.png",
    "time": "04:45:28",
    "last_update": "04:45:28",
    "peak_temp": 11.0,
    "peak_status": "ΞΑΣΤΕΡΙΑ.ΑΙΘΡΙΟΣ",
    "feels_like": 11.0,
    "wind_info": "ΒΔ 9.8 km/h",
    "model_forecast": "ΠΙΘΑΝΗ ΕΠΙΔΕΙΝΩΣΗ ΑΠΟ ΠΕΜΠΤΗ"
}