{
    "temperature": 12.7,
    "temp_max": 19.8,
    "temp_min": 11.6,
    "humidity": 97,
    "pressure": 1029.9,
    "dew_point": 12.1,
    "wind_speed": 4.3,
    "wind_gust": 11.9,
    "wind_dir": 345,
    "wind_text": "345° Β",
    "rain": 0.0,
    "clouds": 31,
    "status": "ΛΙΓΑ ΣΥΝΝΕΦΑ",
    "moon_icon": "moon2.png",
    "time": "01:41:28",
    "last_update": "01:41:28",
    "peak_temp": 12.7,
    "peak_status": "ΛΙΓΑ ΣΥΝΝΕΦΑ",
    "feels_like": 12.7,
    "wind_info": "Β 4.3 km/h",
    "model_forecast": "ΠΡΟΣΟΧΗ: ΦΑΙΝΟΜΕΝΑ ΣΕ ΕΞΕΛΙΞΗ"
}