{
    "model_forecast": "ΠΙΘΑΝΗ ΕΠΙΔΕΙΝΩΣΗ ΑΠΟ ΤΡΙΤΗ",
    "temperature": 3.3,
    "temp_max": 14.0,
    "temp_min": 1.6,
    "humidity": 72,
    "pressure": 1022.0,
    "dew_point": -2.3,
    "wind_speed": 3.3,
    "wind_gust": 16.2,
    "wind_dir": 49,
    "wind_text": "49° ΒΑ",
    "rain": 0.0,
    "clouds": 0,
    "status": "ΞΑΣΤΕΡΙΑ.ΑΙΘΡΙΟΣ",
    "moon_icon": "moon5.png",
    "time": "02:04:24",
    "last_update": "02:04:24",
    "peak_temp": 2.8,
    "peak_status": "ΞΑΣΤΕΡΙΑ.ΑΙΘΡΙΟΣ",
    "feels_like": 3.3,
    "wind_info": "ΒΑ 3.3 km/h"
}