{
    "temperature": 15.4,
    "temp_max": 20.6,
    "temp_min": 7.9,
    "humidity": 62,
    "pressure": 1028.7,
    "dew_point": 7.8,
    "wind_speed": 4.4,
    "wind_gust": 14.4,
    "wind_dir": 322,
    "wind_text": "322° ΒΔ",
    "rain": 0.0,
    "clouds": 0,
    "status": "ΞΑΣΤΕΡΙΑ.ΑΙΘΡΙΟΣ",
    "moon_icon": "moon5.png",
    "time": "10:00:36",
    "last_update": "10:00:36",
    "peak_temp": 15.4,
    "peak_status": "ΞΑΣΤΕΡΙΑ.ΑΙΘΡΙΟΣ",
    "feels_like": 15.4,
    "wind_info": "ΒΔ 4.4 km/h",
    "model_forecast": "ΠΙΘΑΝΗ ΕΠΙΔΕΙΝΩΣΗ ΑΠΟ ΤΡΙΤΗ"
}