{
    "temperature": 11.9,
    "temp_max": 16.9,
    "temp_min": 10.6,
    "humidity": 79,
    "pressure": 1025.9,
    "dew_point": 7.7,
    "wind_speed": 0.9,
    "wind_gust": 6.5,
    "wind_dir": 169,
    "wind_text": "169° Ν",
    "rain": 0.1,
    "clouds": 100,
    "status": "ΕΠΙΔΕΙΝΩΣΗ",
    "moon_icon": "moon7.png",
    "time": "06:15:29",
    "last_update": "06:15:29",
    "peak_temp": 11.9,
    "peak_status": "ΒΡΟΧΗ",
    "feels_like": 11.9,
    "wind_info": "Ν 0.9 km/h",
    "model_forecast": "ΠΙΘΑΝΗ ΕΠΙΔΕΙΝΩΣΗ ΑΠΟ ΠΑΡΑΣΚΕΥΗ"
}