{
    "temperature": 8.4,
    "temp_max": 12.8,
    "temp_min": 4.4,
    "humidity": 78,
    "pressure": 1024.0,
    "dew_point": 4.0,
    "wind_speed": 9.0,
    "wind_gust": 23.4,
    "wind_dir": 355,
    "wind_text": "355° Β",
    "rain": 0.0,
    "clouds": 21,
    "status": "ΞΑΣΤΕΡΙΑ.ΑΙΘΡΙΟΣ",
    "moon_icon": "moon3.png",
    "time": "09:45:27",
    "last_update": "09:45:27",
    "peak_temp": 8.4,
    "peak_status": "ΞΑΣΤΕΡΙΑ.ΑΙΘΡΙΟΣ",
    "feels_like": 8.4,
    "wind_info": "Β 9.0 km/h",
    "model_forecast": "ΠΙΘΑΝΗ ΕΠΙΔΕΙΝΩΣΗ ΑΠΟ ΚΥΡΙΑΚΗ"
}