{
    "temperature": 4.1,
    "temp_max": 15.0,
    "temp_min": 3.3,
    "humidity": 70,
    "pressure": 1028.6,
    "dew_point": -1.9,
    "wind_speed": 2.6,
    "wind_gust": 10.1,
    "wind_dir": 286,
    "wind_text": "286° Δ",
    "rain": 0.0,
    "clouds": 0,
    "status": "ΞΑΣΤΕΡΙΑ.ΑΙΘΡΙΟΣ",
    "moon_icon": "moon3.png",
    "time": "03:00:42",
    "last_update": "03:00:42",
    "peak_temp": 4.1,
    "peak_status": "ΞΑΣΤΕΡΙΑ.ΑΙΘΡΙΟΣ",
    "feels_like": 4.1,
    "wind_info": "Δ 2.6 km/h",
    "model_forecast": "ΞΑΣΤΕΡΙΑ.ΑΙΘΡΙΟΣ"
}