{
    "temperature": 21.5,
    "temp_max": 21.5,
    "temp_min": 12.9,
    "humidity": 62,
    "pressure": 1023.2,
    "dew_point": 13.9,
    "wind_speed": 7.5,
    "wind_gust": 24.1,
    "wind_dir": 147,
    "wind_text": "147° ΝΑ",
    "rain": 0.1,
    "clouds": 82,
    "status": "ΕΠΙΔΕΙΝΩΣΗ",
    "moon_icon": "moon5.png",
    "time": "14:00:56",
    "last_update": "14:00:56",
    "peak_temp": 21.5,
    "peak_status": "ΚΑΤΑΙΓΙΔΑ",
    "feels_like": 21.5,
    "wind_info": "ΝΑ 7.5 km/h",
    "model_forecast": "ΚΑΤΑΙΓΙΔΑ"
}