{
    "temperature": 25.8,
    "temp_max": 27.4,
    "temp_min": 17.9,
    "humidity": 46,
    "pressure": 1035.3,
    "dew_point": 15.0,
    "wind_speed": 10.0,
    "wind_gust": 25.9,
    "wind_dir": 76,
    "wind_text": "76° Α",
    "rain": 0.0,
    "clouds": 2,
    "status": "ΞΑΣΤΕΡΙΑ.ΑΙΘΡΙΟΣ",
    "moon_icon": "moon4.png",
    "time": "12:01:03",
    "last_update": "12:01:03",
    "peak_temp": 25.8,
    "peak_status": "ΞΑΣΤΕΡΙΑ.ΑΙΘΡΙΟΣ",
    "feels_like": 25.8,
    "wind_info": "Α 10.0 km/h",
    "model_forecast": "ΠΙΘΑΝΗ ΕΠΙΔΕΙΝΩΣΗ ΑΠΟ ΤΕΤΑΡΤΗ"
}