{
    "temperature": 14.3,
    "temp_max": 19.9,
    "temp_min": 11.3,
    "humidity": 72,
    "pressure": 1020.4,
    "dew_point": 8.7,
    "wind_speed": 8.1,
    "wind_gust": 20.5,
    "wind_dir": 137,
    "wind_text": "137° ΝΑ",
    "rain": 0.0,
    "clouds": 22,
    "status": "ΛΙΓΑ ΣΥΝΝΕΦΑ",
    "moon_icon": "moon1.png",
    "time": "08:30:34",
    "last_update": "08:30:34",
    "peak_temp": 14.3,
    "peak_status": "ΛΙΓΑ ΣΥΝΝΕΦΑ",
    "feels_like": 14.3,
    "wind_info": "ΝΑ 8.1 km/h",
    "model_forecast": "ΠΙΘΑΝΗ ΕΠΙΔΕΙΝΩΣΗ ΑΠΟ ΤΡΙΤΗ"
}