{
    "temperature": 12.6,
    "temp_max": 21.3,
    "temp_min": 12.6,
    "humidity": 83,
    "pressure": 1036.4,
    "dew_point": 9.2,
    "wind_speed": 3.3,
    "wind_gust": 8.3,
    "wind_dir": 324,
    "wind_text": "324° ΒΔ",
    "rain": 0.0,
    "clouds": 40,
    "status": "ΛΙΓΑ ΣΥΝΝΕΦΑ",
    "moon_icon": "moon2.png",
    "time": "06:00:44",
    "last_update": "06:00:44",
    "peak_temp": 12.6,
    "peak_status": "ΛΙΓΑ ΣΥΝΝΕΦΑ",
    "feels_like": 12.6,
    "wind_info": "ΒΔ 3.3 km/h",
    "model_forecast": "ΠΙΘΑΝΗ ΕΠΙΔΕΙΝΩΣΗ ΑΠΟ ΠΕΜΠΤΗ"
}