{
    "temperature": 3.0,
    "temp_max": 9.8,
    "temp_min": 2.9,
    "humidity": 99,
    "pressure": 1031.2,
    "dew_point": 2.8,
    "wind_speed": 1.1,
    "wind_gust": 8.6,
    "wind_dir": 81,
    "wind_text": "81° Α",
    "rain": 0.0,
    "clouds": 77,
    "status": "ΕΠΙΔΕΙΝΩΣΗ",
    "moon_icon": "moon4.png",
    "time": "04:15:31",
    "last_update": "04:15:31",
    "peak_temp": 3.0,
    "peak_status": "ΛΙΓΑ ΣΥΝΝΕΦΑ",
    "feels_like": 3.0,
    "wind_info": "Α 1.1 km/h",
    "model_forecast": "ΠΡΟΣΟΧΗ: ΦΑΙΝΟΜΕΝΑ ΣΕ ΕΞΕΛΙΞΗ"
}