{
    "temperature": 16.8,
    "temp_max": 27.3,
    "temp_min": 16.5,
    "humidity": 72,
    "pressure": 1027.8,
    "dew_point": 11.2,
    "wind_speed": 1.9,
    "wind_gust": 7.2,
    "wind_dir": 221,
    "wind_text": "221° ΝΔ",
    "rain": 0.0,
    "clouds": 2,
    "status": "ΞΑΣΤΕΡΙΑ.ΑΙΘΡΙΟΣ",
    "moon_icon": "moon1.png",
    "time": "04:15:40",
    "last_update": "04:15:40",
    "peak_temp": 16.8,
    "peak_status": "ΞΑΣΤΕΡΙΑ.ΑΙΘΡΙΟΣ",
    "feels_like": 16.8,
    "wind_info": "ΝΔ 1.9 km/h",
    "model_forecast": "ΠΙΘΑΝΗ ΕΠΙΔΕΙΝΩΣΗ ΑΠΟ ΤΕΤΑΡΤΗ"
}