{
    "temperature": 17.1,
    "temp_max": 19.2,
    "temp_min": 11.2,
    "humidity": 70,
    "pressure": 1016.7,
    "dew_point": 11.1,
    "wind_speed": 23.3,
    "wind_gust": 58.0,
    "wind_dir": 262,
    "wind_text": "262° Δ",
    "rain": 0.2,
    "clouds": 55,
    "status": "ΒΡΟΧΗ",
    "moon_icon": "moon0.png",
    "time": "17:08:53",
    "last_update": "17:08:53",
    "peak_temp": 17.1,
    "peak_status": "ΒΡΟΧΗ",
    "feels_like": 17.1,
    "wind_info": "Δ 23.3 km/h",
    "model_forecast": "ΠΡΟΣΟΧΗ: ΦΑΙΝΟΜΕΝΑ ΣΕ ΕΞΕΛΙΞΗ"
}