{
    "temperature": 16.5,
    "temp_max": 21.1,
    "temp_min": 10.5,
    "humidity": 32,
    "pressure": 1030.0,
    "dew_point": 2.9,
    "wind_speed": 12.4,
    "wind_gust": 34.6,
    "wind_dir": 292,
    "wind_text": "292° Δ",
    "rain": 0.0,
    "clouds": 0,
    "status": "ΞΑΣΤΕΡΙΑ.ΑΙΘΡΙΟΣ",
    "moon_icon": "moon3.png",
    "time": "20:41:08",
    "last_update": "20:41:08",
    "peak_temp": 16.5,
    "peak_status": "ΞΑΣΤΕΡΙΑ.ΑΙΘΡΙΟΣ",
    "feels_like": 16.5,
    "wind_info": "Δ 12.4 km/h",
    "model_forecast": "ΠΙΘΑΝΗ ΕΠΙΔΕΙΝΩΣΗ ΑΠΟ ΤΕΤΑΡΤΗ"
}