{
    "temperature": 18.5,
    "temp_max": 21.8,
    "temp_min": 14.3,
    "humidity": 78,
    "pressure": 1028.4,
    "dew_point": 14.1,
    "wind_speed": 2.9,
    "wind_gust": 8.3,
    "wind_dir": 184,
    "wind_text": "184° Ν",
    "rain": 0.0,
    "clouds": 2,
    "status": "ΞΑΣΤΕΡΙΑ.ΑΙΘΡΙΟΣ",
    "moon_icon": "moon1.png",
    "time": "00:01:34",
    "last_update": "00:01:34",
    "peak_temp": 18.5,
    "peak_status": "ΞΑΣΤΕΡΙΑ.ΑΙΘΡΙΟΣ",
    "feels_like": 18.5,
    "wind_info": "Ν 2.9 km/h",
    "model_forecast": "ΞΑΣΤΕΡΙΑ.ΑΙΘΡΙΟΣ"
}