{
    "temperature": 20.2,
    "temp_max": 26.8,
    "temp_min": 17.2,
    "humidity": 64,
    "pressure": 1030.3,
    "dew_point": 13.0,
    "wind_speed": 7.1,
    "wind_gust": 14.8,
    "wind_dir": 300,
    "wind_text": "300° ΒΔ",
    "rain": 0.0,
    "clouds": 86,
    "status": "ΕΠΙΔΕΙΝΩΣΗ",
    "moon_icon": "moon7.png",
    "time": "08:01:03",
    "last_update": "08:01:03",
    "peak_temp": 20.2,
    "peak_status": "ΛΙΓΑ ΣΥΝΝΕΦΑ",
    "feels_like": 20.2,
    "wind_info": "ΒΔ 7.1 km/h",
    "model_forecast": "ΠΙΘΑΝΗ ΕΠΙΔΕΙΝΩΣΗ ΑΠΟ ΤΕΤΑΡΤΗ"
}