{
    "temperature": 16.8,
    "temp_max": 17.2,
    "temp_min": 8.9,
    "humidity": 59,
    "pressure": 1033.6,
    "dew_point": 8.6,
    "wind_speed": 8.6,
    "wind_gust": 23.0,
    "wind_dir": 170,
    "wind_text": "170° Ν",
    "rain": 0.1,
    "clouds": 48,
    "status": "ΒΡΟΧΗ",
    "moon_icon": "moon5.png",
    "time": "13:00:39",
    "last_update": "13:00:39",
    "peak_temp": 16.8,
    "peak_status": "ΒΡΟΧΗ",
    "feels_like": 16.8,
    "wind_info": "Ν 8.6 km/h",
    "model_forecast": "ΠΙΘΑΝΗ ΕΠΙΔΕΙΝΩΣΗ ΑΠΟ ΤΕΤΑΡΤΗ"
}