{
    "temperature": 15.2,
    "temp_max": 20.6,
    "temp_min": 7.9,
    "humidity": 62,
    "pressure": 1028.6,
    "dew_point": 7.6,
    "wind_speed": 4.2,
    "wind_gust": 14.0,
    "wind_dir": 320,
    "wind_text": "320° ΒΔ",
    "rain": 0.0,
    "clouds": 0,
    "status": "ΞΑΣΤΕΡΙΑ.ΑΙΘΡΙΟΣ",
    "moon_icon": "moon5.png",
    "time": "09:45:24",
    "last_update": "09:45:24",
    "peak_temp": 15.2,
    "peak_status": "ΞΑΣΤΕΡΙΑ.ΑΙΘΡΙΟΣ",
    "feels_like": 15.2,
    "wind_info": "ΒΔ 4.2 km/h",
    "model_forecast": "ΠΙΘΑΝΗ ΕΠΙΔΕΙΝΩΣΗ ΑΠΟ ΤΡΙΤΗ"
}