{
    "temperature": 19.7,
    "temp_max": 26.5,
    "temp_min": 18.2,
    "humidity": 69,
    "pressure": 1032.0,
    "dew_point": 13.5,
    "wind_speed": 2.3,
    "wind_gust": 6.1,
    "wind_dir": 274,
    "wind_text": "274° Δ",
    "rain": 0.0,
    "clouds": 0,
    "status": "ΞΑΣΤΕΡΙΑ.ΑΙΘΡΙΟΣ",
    "moon_icon": "moon6.png",
    "time": "07:15:30",
    "last_update": "07:15:30",
    "peak_temp": 19.7,
    "peak_status": "ΞΑΣΤΕΡΙΑ.ΑΙΘΡΙΟΣ",
    "feels_like": 19.7,
    "wind_info": "Δ 2.3 km/h",
    "model_forecast": "ΠΙΘΑΝΗ ΕΠΙΔΕΙΝΩΣΗ ΑΠΟ ΔΕΥΤΕΡΑ"
}