{
    "temperature": 5.1,
    "temp_max": 10.9,
    "temp_min": 3.3,
    "humidity": 78,
    "pressure": 1028.7,
    "dew_point": 0.7,
    "wind_speed": 2.2,
    "wind_gust": 4.7,
    "wind_dir": 166,
    "wind_text": "166° Ν",
    "rain": 0.0,
    "clouds": 0,
    "status": "ΞΑΣΤΕΡΙΑ.ΑΙΘΡΙΟΣ",
    "moon_icon": "moon3.png",
    "time": "21:15:27",
    "last_update": "21:15:27",
    "peak_temp": 5.1,
    "peak_status": "ΞΑΣΤΕΡΙΑ.ΑΙΘΡΙΟΣ",
    "feels_like": 5.1,
    "wind_info": "Ν 2.2 km/h",
    "model_forecast": "ΞΑΣΤΕΡΙΑ.ΑΙΘΡΙΟΣ"
}