{
    "temperature": 8.6,
    "temp_max": 18.5,
    "temp_min": 8.1,
    "humidity": 76,
    "pressure": 1028.9,
    "dew_point": 3.8,
    "wind_speed": 0.7,
    "wind_gust": 2.9,
    "wind_dir": 194,
    "wind_text": "194° Ν",
    "rain": 0.0,
    "clouds": 1,
    "status": "ΞΑΣΤΕΡΙΑ.ΑΙΘΡΙΟΣ",
    "moon_icon": "moon5.png",
    "time": "06:00:37",
    "last_update": "06:00:37",
    "peak_temp": 8.6,
    "peak_status": "ΞΑΣΤΕΡΙΑ.ΑΙΘΡΙΟΣ",
    "feels_like": 8.6,
    "wind_info": "Ν 0.7 km/h",
    "model_forecast": "ΠΙΘΑΝΗ ΕΠΙΔΕΙΝΩΣΗ ΑΠΟ ΤΕΤΑΡΤΗ"
}