{
    "temperature": 27.1,
    "temp_max": 27.3,
    "temp_min": 18.4,
    "humidity": 36,
    "pressure": 1026.7,
    "dew_point": 14.3,
    "wind_speed": 11.1,
    "wind_gust": 27.0,
    "wind_dir": 278,
    "wind_text": "278° Δ",
    "rain": 0.0,
    "clouds": 23,
    "status": "ΛΙΓΑ ΣΥΝΝΕΦΑ",
    "moon_icon": "moon6.png",
    "time": "17:55:14",
    "last_update": "17:55:14",
    "peak_temp": 27.1,
    "peak_status": "ΛΙΓΑ ΣΥΝΝΕΦΑ",
    "feels_like": 27.1,
    "wind_info": "Δ 11.1 km/h",
    "model_forecast": "ΠΙΘΑΝΗ ΕΠΙΔΕΙΝΩΣΗ ΑΠΟ ΠΑΡΑΣΚΕΥΗ"
}