{
    "temperature": 18.7,
    "temp_max": 19.0,
    "temp_min": 12.0,
    "humidity": 57,
    "pressure": 1032.3,
    "dew_point": 10.1,
    "wind_speed": 7.1,
    "wind_gust": 22.0,
    "wind_dir": 322,
    "wind_text": "322° ΒΔ",
    "rain": 0.1,
    "clouds": 100,
    "status": "ΕΠΙΔΕΙΝΩΣΗ",
    "moon_icon": "moon6.png",
    "time": "13:15:30",
    "last_update": "13:15:30",
    "peak_temp": 18.7,
    "peak_status": "ΒΡΟΧΗ",
    "feels_like": 18.7,
    "wind_info": "ΒΔ 7.1 km/h",
    "model_forecast": "ΠΙΘΑΝΗ ΕΠΙΔΕΙΝΩΣΗ ΑΠΟ ΣΑΒΒΑΤΟ"
}