{
    "temperature": 19.1,
    "temp_max": 19.1,
    "temp_min": 8.5,
    "humidity": 49,
    "pressure": 1025.0,
    "dew_point": 8.9,
    "wind_speed": 20.3,
    "wind_gust": 45.0,
    "wind_dir": 270,
    "wind_text": "270° Δ",
    "rain": 0.2,
    "clouds": 48,
    "status": "ΒΡΟΧΗ",
    "moon_icon": "moon7.png",
    "time": "14:00:37",
    "last_update": "14:00:37",
    "peak_temp": 19.1,
    "peak_status": "ΒΡΟΧΗ",
    "feels_like": 19.1,
    "wind_info": "Δ 20.3 km/h",
    "model_forecast": "ΠΡΟΣΟΧΗ: ΦΑΙΝΟΜΕΝΑ ΣΕ ΕΞΕΛΙΞΗ"
}