{
    "temperature": 14.1,
    "temp_max": 14.3,
    "temp_min": 6.4,
    "humidity": 70,
    "pressure": 1029.6,
    "dew_point": 8.1,
    "wind_speed": 17.0,
    "wind_gust": 40.0,
    "wind_dir": 129,
    "wind_text": "129° ΝΑ",
    "rain": 0.0,
    "clouds": 100,
    "status": "ΕΠΙΔΕΙΝΩΣΗ",
    "moon_icon": "moon1.png",
    "time": "16:45:29",
    "last_update": "16:45:29",
    "peak_temp": 14.1,
    "peak_status": "ΛΙΓΑ ΣΥΝΝΕΦΑ",
    "feels_like": 14.1,
    "wind_info": "ΝΑ 17.0 km/h",
    "model_forecast": "ΠΙΘΑΝΗ ΕΠΙΔΕΙΝΩΣΗ ΑΠΟ ΤΕΤΑΡΤΗ"
}