{
    "temperature": 16.0,
    "temp_max": 22.8,
    "temp_min": 13.9,
    "humidity": 69,
    "pressure": 1029.3,
    "dew_point": 9.8,
    "wind_speed": 6.6,
    "wind_gust": 15.1,
    "wind_dir": 343,
    "wind_text": "343° Β",
    "rain": 0.0,
    "clouds": 7,
    "status": "ΞΑΣΤΕΡΙΑ.ΑΙΘΡΙΟΣ",
    "moon_icon": "moon5.png",
    "time": "03:30:34",
    "last_update": "03:30:34",
    "peak_temp": 16.0,
    "peak_status": "ΞΑΣΤΕΡΙΑ.ΑΙΘΡΙΟΣ",
    "feels_like": 16.0,
    "wind_info": "Β 6.6 km/h",
    "model_forecast": "ΞΑΣΤΕΡΙΑ.ΑΙΘΡΙΟΣ"
}