{
    "temperature": 16.6,
    "temp_max": 16.7,
    "temp_min": 7.5,
    "humidity": 49,
    "pressure": 1028.3,
    "dew_point": 6.4,
    "wind_speed": 5.3,
    "wind_gust": 19.1,
    "wind_dir": 308,
    "wind_text": "308° ΒΔ",
    "rain": 0.0,
    "clouds": 17,
    "status": "ΞΑΣΤΕΡΙΑ.ΑΙΘΡΙΟΣ",
    "moon_icon": "moon7.png",
    "time": "16:45:28",
    "last_update": "16:45:28",
    "peak_temp": 16.6,
    "peak_status": "ΞΑΣΤΕΡΙΑ.ΑΙΘΡΙΟΣ",
    "feels_like": 16.6,
    "wind_info": "ΒΔ 5.3 km/h",
    "model_forecast": "ΠΙΘΑΝΗ ΕΠΙΔΕΙΝΩΣΗ ΑΠΟ ΔΕΥΤΕΡΑ"
}