{
    "temperature": 25.0,
    "temp_max": 25.4,
    "temp_min": 16.3,
    "humidity": 35,
    "pressure": 1029.7,
    "dew_point": 12.0,
    "wind_speed": 11.4,
    "wind_gust": 28.1,
    "wind_dir": 347,
    "wind_text": "347° Β",
    "rain": 0.0,
    "clouds": 11,
    "status": "ΞΑΣΤΕΡΙΑ.ΑΙΘΡΙΟΣ",
    "moon_icon": "moon5.png",
    "time": "14:30:37",
    "last_update": "14:30:37",
    "peak_temp": 25.0,
    "peak_status": "ΞΑΣΤΕΡΙΑ.ΑΙΘΡΙΟΣ",
    "feels_like": 25.0,
    "wind_info": "Β 11.4 km/h",
    "model_forecast": "ΞΑΣΤΕΡΙΑ.ΑΙΘΡΙΟΣ"
}