{
    "temperature": 19.8,
    "temp_max": 24.5,
    "temp_min": 15.4,
    "humidity": 63,
    "pressure": 1030.8,
    "dew_point": 12.4,
    "wind_speed": 1.1,
    "wind_gust": 6.8,
    "wind_dir": 72,
    "wind_text": "72° Α",
    "rain": 0.0,
    "clouds": 2,
    "status": "ΞΑΣΤΕΡΙΑ.ΑΙΘΡΙΟΣ",
    "moon_icon": "moon6.png",
    "time": "21:45:36",
    "last_update": "21:45:36",
    "peak_temp": 19.8,
    "peak_status": "ΞΑΣΤΕΡΙΑ.ΑΙΘΡΙΟΣ",
    "feels_like": 19.8,
    "wind_info": "Α 1.1 km/h",
    "model_forecast": "ΞΑΣΤΕΡΙΑ.ΑΙΘΡΙΟΣ"
}