{
    "temperature": 23.1,
    "temp_max": 26.5,
    "temp_min": 18.2,
    "humidity": 61,
    "pressure": 1033.5,
    "dew_point": 15.3,
    "wind_speed": 3.3,
    "wind_gust": 14.0,
    "wind_dir": 338,
    "wind_text": "338° Β",
    "rain": 0.0,
    "clouds": 0,
    "status": "ΞΑΣΤΕΡΙΑ.ΑΙΘΡΙΟΣ",
    "moon_icon": "moon6.png",
    "time": "10:00:46",
    "last_update": "10:00:46",
    "peak_temp": 23.1,
    "peak_status": "ΞΑΣΤΕΡΙΑ.ΑΙΘΡΙΟΣ",
    "feels_like": 23.1,
    "wind_info": "Β 3.3 km/h",
    "model_forecast": "ΠΙΘΑΝΗ ΕΠΙΔΕΙΝΩΣΗ ΑΠΟ ΔΕΥΤΕΡΑ"
}