{
    "temperature": 10.6,
    "temp_max": 13.5,
    "temp_min": 8.2,
    "humidity": 89,
    "pressure": 1025.0,
    "dew_point": 8.4,
    "wind_speed": 13.5,
    "wind_gust": 32.4,
    "wind_dir": 16,
    "wind_text": "16° Β",
    "rain": 0.2,
    "clouds": 100,
    "status": "ΒΡΟΧΗ",
    "moon_icon": "moon7.png",
    "time": "14:15:28",
    "last_update": "14:15:28",
    "peak_temp": 10.6,
    "peak_status": "ΒΡΟΧΗ",
    "feels_like": 10.6,
    "wind_info": "Β 13.5 km/h",
    "model_forecast": "ΠΡΟΣΟΧΗ: ΦΑΙΝΟΜΕΝΑ ΣΕ ΕΞΕΛΙΞΗ"
}