{
    "temperature": 18.6,
    "temp_max": 23.3,
    "temp_min": 12.9,
    "humidity": 71,
    "pressure": 1029.6,
    "dew_point": 12.8,
    "wind_speed": 10.1,
    "wind_gust": 28.8,
    "wind_dir": 265,
    "wind_text": "265° Δ",
    "rain": 0.0,
    "clouds": 4,
    "status": "ΞΑΣΤΕΡΙΑ.ΑΙΘΡΙΟΣ",
    "moon_icon": "moon4.png",
    "time": "20:15:27",
    "last_update": "20:15:27",
    "peak_temp": 18.6,
    "peak_status": "ΞΑΣΤΕΡΙΑ.ΑΙΘΡΙΟΣ",
    "feels_like": 18.6,
    "wind_info": "Δ 10.1 km/h",
    "model_forecast": "ΞΑΣΤΕΡΙΑ.ΑΙΘΡΙΟΣ"
}