{
    "temperature": 15.2,
    "temp_max": 23.7,
    "temp_min": 14.8,
    "humidity": 78,
    "pressure": 1037.0,
    "dew_point": 10.8,
    "wind_speed": 0.6,
    "wind_gust": 5.8,
    "wind_dir": 146,
    "wind_text": "146° ΝΑ",
    "rain": 0.0,
    "clouds": 14,
    "status": "ΞΑΣΤΕΡΙΑ.ΑΙΘΡΙΟΣ",
    "moon_icon": "moon5.png",
    "time": "00:00:42",
    "last_update": "00:00:42",
    "peak_temp": 15.2,
    "peak_status": "ΞΑΣΤΕΡΙΑ.ΑΙΘΡΙΟΣ",
    "feels_like": 15.2,
    "wind_info": "ΝΑ 0.6 km/h",
    "model_forecast": "ΠΙΘΑΝΗ ΕΠΙΔΕΙΝΩΣΗ ΑΠΟ ΤΕΤΑΡΤΗ"
}