{
    "temperature": 14.2,
    "temp_max": 20.7,
    "temp_min": 11.7,
    "humidity": 92,
    "pressure": 1027.6,
    "dew_point": 12.6,
    "wind_speed": 4.0,
    "wind_gust": 9.0,
    "wind_dir": 150,
    "wind_text": "150° ΝΑ",
    "rain": 0.0,
    "clouds": 2,
    "status": "ΞΑΣΤΕΡΙΑ.ΑΙΘΡΙΟΣ",
    "moon_icon": "moon6.png",
    "time": "22:30:36",
    "last_update": "22:30:36",
    "peak_temp": 14.2,
    "peak_status": "ΞΑΣΤΕΡΙΑ.ΑΙΘΡΙΟΣ",
    "feels_like": 14.2,
    "wind_info": "ΝΑ 4.0 km/h",
    "model_forecast": "ΞΑΣΤΕΡΙΑ.ΑΙΘΡΙΟΣ"
}