{
    "temperature": 19.9,
    "temp_max": 25.0,
    "temp_min": 16.3,
    "humidity": 53,
    "pressure": 1031.9,
    "dew_point": 10.5,
    "wind_speed": 6.7,
    "wind_gust": 16.6,
    "wind_dir": 341,
    "wind_text": "341° Β",
    "rain": 0.0,
    "clouds": 0,
    "status": "ΞΑΣΤΕΡΙΑ.ΑΙΘΡΙΟΣ",
    "moon_icon": "moon6.png",
    "time": "09:01:14",
    "last_update": "09:01:14",
    "peak_temp": 19.9,
    "peak_status": "ΞΑΣΤΕΡΙΑ.ΑΙΘΡΙΟΣ",
    "feels_like": 19.9,
    "wind_info": "Β 6.7 km/h",
    "model_forecast": "ΞΑΣΤΕΡΙΑ.ΑΙΘΡΙΟΣ"
}