{
    "temperature": 7.8,
    "temp_max": 17.4,
    "temp_min": 6.5,
    "humidity": 67,
    "pressure": 1025.5,
    "dew_point": 1.2,
    "wind_speed": 2.3,
    "wind_gust": 7.9,
    "wind_dir": 309,
    "wind_text": "309° ΒΔ",
    "rain": 0.0,
    "clouds": 38,
    "status": "ΛΙΓΑ ΣΥΝΝΕΦΑ",
    "moon_icon": "moon2.png",
    "time": "05:45:28",
    "last_update": "05:45:28",
    "peak_temp": 7.8,
    "peak_status": "ΛΙΓΑ ΣΥΝΝΕΦΑ",
    "feels_like": 7.8,
    "wind_info": "ΒΔ 2.3 km/h",
    "model_forecast": "ΛΙΓΑ ΣΥΝΝΕΦΑ"
}