{
    "temperature": 20.6,
    "temp_max": 20.9,
    "temp_min": 11.7,
    "humidity": 43,
    "pressure": 1031.9,
    "dew_point": 9.2,
    "wind_speed": 11.2,
    "wind_gust": 28.1,
    "wind_dir": 345,
    "wind_text": "345° Β",
    "rain": 0.0,
    "clouds": 3,
    "status": "ΞΑΣΤΕΡΙΑ.ΑΙΘΡΙΟΣ",
    "moon_icon": "moon1.png",
    "time": "15:00:53",
    "last_update": "15:00:53",
    "peak_temp": 20.6,
    "peak_status": "ΞΑΣΤΕΡΙΑ.ΑΙΘΡΙΟΣ",
    "feels_like": 20.6,
    "wind_info": "Β 11.2 km/h",
    "model_forecast": "ΞΑΣΤΕΡΙΑ.ΑΙΘΡΙΟΣ"
}